{"Player": {"tools": ["axe", "hoe", "water"], "tool_idx": 2, "seeds": ["corn", "tomato"], "seed_idx": 0, "item_inventory": {"wood": 46, "apple": 14, "corn": 15, "tomato": 12}, "seed_inventory": {"corn": 7, "tomato": 6}, "money": 160, "pos": [1425, 1411], "status": "left_idle"}, "Soil": {"grid": [[[], [], [], [], [], [], [], [], [], [], [], [], [], [], [], [], [], [], [], [], [], [], [], [], [], [], [], [], [], [], [], [], [], [], [], [], [], [], [], [], [], [], [], [], [], [], [], [], [], []], [[], [], [], [], [], [], [], [], [], [], [], [], [], [], [], [], [], [], [], [], [], [], [], [], [], [], [], [], [], [], [], [], [], [], [], [], [], [], [], [], [], [], [], [], [], [], [], [], [], []], [[], [], [], [], [], [], [], [], [], [], [], [], [], [], [], [], [], [], [], [], [], [], [], [], [], [], [], [], [], [], [], [], [], [], [], [], [], [], [], [], [], [], [], [], [], [], [], [], [], []], [[], [], [], [], [], [], [], [], [], [], [], [], [], [], [], [], [], [], [], [], [], [], [], [], [], [], [], [], [], [], [], [], [], [], [], [], [], [], [], [], [], [], [], [], [], [], [], [], [], []], [[], [], [], [], [], [], [], [], [], [], [], [], [], [], [], [], [], [], [], [], [], [], [], [], [], [], [], [], [], [], [], [], [], [], [], [], [], [], [], [], [], [], [], [], [], [], [], [], [], []], [[], [], [], [], [], [], [], [], [], [], [], [], [], [], [], [], [], [], [], [], [], [], [], [], [], [], [], [], [], [], [], [], [], [], [], [], [], [], [], [], [], [], [], [], [], [], [], [], [], []], [[], [], [], [], [], [], [], [], [], [], [], [], [], [], [], [], [], [], [], [], [], [], [], [], [], [], [], [], [], [], [], [], [], [], [], [], [], [], [], [], [], [], [], [], [], [], [], [], [], []], [[], [], [], [], [], [], [], [], [], [], [], [], [], [], [], [], [], [], [], [], [], [], [], [], [], [], [], [], [], [], [], [], [], [], [], [], [], [], [], [], [], [], [], [], [], [], [], [], [], []], [[], [], [], [], [], [], [], [], [], [], [], [], [], [], [], [], [], [], [], [], [], [], [], [], [], [], [], [], [], [], [], [], [], [], [], [], [], [], [], [], [], [], [], [], [], [], [], [], [], []], [[], [], [], [], [], [], [], [], [], [], [], [], [], [], [], [], [], [], [], [], [], [], [], [], [], [], [], [], [], [], [], [], [], [], [], [], [], [], [], [], [], [], [], [], [], [], [], [], [], []], [[], [], [], [], [], [], [], [], [], [], [], [], [], [], [], [], [], [], [], [], [], [], [], [], [], [], [], [], [], [], [], [], [], [], [], [], [], [], [], [], [], [], [], [], [], [], [], [], [], []], [[], [], [], [], [], [], [], [], [], [], [], [], [], [], [], [], [], [], [], [], [], [], [], [], [], [], [], [], [], [], [], [], [], [], [], [], [], [], [], [], [], [], [], [], [], [], [], [], [], []], [[], [], [], [], [], [], [], [], [], [], [], [], [], [], [], [], [], [], [], [], [], [], [], [], [], [], [], [], [], [], [], [], [], [], [], [], [], [], [], [], [], [], [], [], [], [], [], [], [], []], [[], [], [], [], [], [], [], [], [], [], [], [], [], [], [], [], [], [], [], [], [], [], [], [], [], [], [], [], [], [], [], [], [], [], [], [], [], [], [], [], [], [], [], [], [], [], [], [], [], []], [[], [], [], [], [], [], [], [], [], [], [], [], [], [], ["F"], ["F"], ["F"], ["F"], [], [], [], [], [], [], [], [], [], [], [], [], [], [], [], [], [], [], [], [], [], [], [], [], [], [], [], [], [], [], [], []], [[], [], [], [], [], [], [], [], [], [], [], [], [], ["F"], ["F"], ["F"], ["F"], ["F"], ["F"], [], [], [], [], [], [], [], [], [], ["F"], ["F"], ["F"], ["F"], ["F"], ["F"], [], ["F"], [], [], [], [], [], [], [], [], [], [], [], [], [], []], [[], [], [], [], [], [], [], [], [], [], [], [], ["F"], ["F"], ["F"], ["F"], ["F"], ["F"], ["F"], ["F"], ["F"], ["F"], ["F"], ["F"], ["F"], ["F"], ["F"], ["F"], [], ["F"], ["F"], [], ["F"], ["F"], ["F"], ["F"], [], [], [], [], [], [], [], [], [], [], [], [], [], []], [[], [], [], [], [], [], [], [], [], [], [], ["F"], ["F"], ["F"], ["F"], ["F"], ["F"], ["F"], ["F"], ["F"], ["F"], ["F"], ["F"], ["F"], ["F"], ["F"], ["F"], ["F"], ["F"], ["F"], ["F"], ["F"], ["F"], ["F"], ["F"], ["F"], [], [], [], [], [], [], [], [], [], [], [], [], [], []], [[], [], [], [], [], [], [], [], [], [], [], [], ["F"], ["F"], ["F"], ["F"], ["F"], ["F"], ["F"], ["F"], ["F"], ["F"], ["F"], ["F"], ["F"], ["F"], ["F"], ["F"], ["F"], ["F"], ["F"], ["F"], ["F"], ["F"], ["F"], [], [], [], [], [], [], [], [], [], [], [], [], [], [], []], [[], [], [], [], [], [], [], [], [], [], [], ["F"], ["F"], ["F"], ["F"], ["F"], ["F"], ["F"], ["F"], ["F"], ["F"], ["F"], ["F"], ["F"], ["F"], ["F"], ["F"], ["F"], ["F"], ["F"], ["F"], ["F"], ["F"], ["F"], ["F"], ["F"], [], [], [], [], [], [], [], [], [], [], [], [], [], []], [[], [], [], [], [], [], [], [], [], [], [], ["F"], ["F"], ["F"], ["F"], ["F"], ["F"], ["F"], ["F"], ["F"], ["F"], ["F"], ["F"], ["F"], ["F"], ["F"], ["F"], ["F"], ["F"], ["F"], ["F"], ["F"], ["F"], ["F"], ["F"], ["F"], [], [], [], [], [], [], [], [], [], [], [], [], [], []], [[], [], [], [], [], [], [], [], [], [], [], ["F"], ["F"], ["F"], ["F"], ["F"], ["F"], ["F"], ["F"], ["F"], [], [], [], [], [], [], [], [], ["F"], ["F"], ["F"], ["F"], ["F"], ["F"], ["F"], ["F"], [], [], [], [], [], [], [], [], [], [], [], [], [], []], [[], [], [], [], [], [], [], [], [], [], [], ["F"], ["F"], ["F"], ["F"], ["F"], [], ["F"], ["F"], ["F"], [], [], [], [], [], [], [], [], ["F"], ["F"], ["F"], ["F"], ["F"], ["F"], ["F"], ["F"], [], [], [], [], [], [], [], [], [], [], [], [], [], []], [[], [], [], [], [], [], [], [], [], [], [], ["F"], ["F"], ["F"], ["F"], ["F"], [], ["F"], ["F"], ["F"], [], [], [], [], [], [], [], [], ["F"], ["F"], ["F"], ["F"], ["F"], ["F"], ["F"], ["F"], [], [], [], [], [], [], [], [], [], [], [], [], [], []], [[], [], [], [], [], [], [], [], [], [], [], ["F"], ["F"], ["F"], ["F"], ["F"], [], ["F"], ["F"], ["F"], [], [], [], [], [], [], [], [], ["F"], ["F"], ["F"], ["F"], ["F"], ["F"], ["F"], ["F"], [], [], [], [], [], [], [], [], [], [], [], [], [], []], [[], [], [], [], [], [], [], [], [], [], [], ["F"], ["F"], ["F"], ["F"], ["F"], [], ["F"], ["F"], ["F"], [], [], [], [], [], [], [], [], ["F"], ["F"], ["F"], ["F"], ["F"], ["F"], ["F"], ["F"], [], [], [], [], [], [], [], [], [], [], [], [], [], []], [[], [], [], [], [], [], [], [], [], [], [], ["F"], ["F"], ["F"], ["F"], ["F"], [], ["F"], ["F"], ["F"], [], [], [], [], [], [], [], [], ["F"], ["F"], ["F"], ["F"], ["F"], ["F"], ["F"], ["F"], [], [], [], [], [], [], [], [], [], [], [], [], [], []], [[], [], [], [], [], [], [], [], [], [], [], ["F"], ["F"], ["F"], ["F"], ["F"], [], ["F"], ["F"], ["F"], ["F"], ["F"], ["F"], ["F"], ["F"], [], ["F"], ["F"], ["F"], ["F"], ["F"], ["F"], ["F"], ["F"], ["F"], ["F"], [], [], [], [], [], [], [], [], [], [], [], [], [], []], [[], [], [], [], [], [], [], [], [], [], [], ["F"], ["F"], ["F"], ["F"], ["F"], [], ["F"], ["F"], ["F"], ["F", "X"], ["F", "X"], ["F", "X"], ["F", "X"], ["F"], [], ["F"], ["F"], ["F"], ["F"], ["F"], ["F"], ["F"], ["F"], ["F"], ["F"], ["F"], [], [], [], [], [], [], [], [], [], [], [], [], []], [[], [], [], [], [], [], [], [], [], [], [], ["F"], ["F"], ["F"], ["F"], ["F"], [], ["F"], ["F"], ["F"], ["F", "X"], ["F", "X", "X", "X"], ["F", "X", "P"], ["F", "X", "X", "P"], ["F"], [], ["F"], ["F"], ["F"], ["F"], ["F"], ["F"], ["F"], ["F"], ["F"], ["F"], ["F"], [], [], [], [], [], [], [], [], [], [], [], [], []], [[], [], [], [], [], [], [], [], [], [], ["F"], ["F"], ["F"], ["F"], ["F"], ["F"], [], ["F"], ["F"], ["F"], ["F", "X"], ["F", "X", "P"], ["F", "X", "P"], ["F", "X", "P"], ["F"], [], ["F"], ["F"], ["F"], ["F"], ["F"], ["F"], ["F"], ["F"], ["F"], ["F"], [], ["F"], [], [], [], [], [], [], [], [], [], [], [], []], [[], [], [], [], [], [], [], [], [], [], [], ["F"], ["F"], ["F"], ["F"], ["F"], [], [], [], [], [], [], [], [], [], [], ["F"], ["F"], ["F"], ["F"], ["F"], ["F"], ["F"], ["F"], ["F"], ["F"], ["F"], ["F"], ["F"], [], [], [], [], [], [], [], [], [], [], []], [[], [], [], [], [], [], [], [], [], [], [], ["F"], ["F"], ["F"], ["F"], ["F"], ["F"], ["F"], ["F"], ["F"], ["F"], ["F"], ["F"], ["F"], ["F"], ["F"], ["F"], ["F"], ["F"], ["F"], ["F"], ["F"], ["F"], ["F"], ["F"], ["F"], ["F"], ["F"], ["F"], [], [], [], [], [], [], [], [], [], [], []], [[], [], [], [], [], [], [], [], [], [], [], [], [], [], [], [], [], [], [], [], [], [], [], [], [], [], [], [], [], [], [], [], [], [], [], [], [], [], [], [], [], [], [], [], [], [], [], [], [], []], [[], [], [], [], [], [], [], [], [], [], [], [], [], [], [], [], [], [], [], [], [], [], [], [], [], [], [], [], [], [], [], [], [], [], [], [], [], [], [], [], [], [], [], [], [], [], [], [], [], []], [[], [], [], [], [], [], [], [], [], [], [], [], [], [], [], [], [], [], [], [], [], [], [], [], [], [], [], [], [], [], [], [], [], [], [], [], [], [], [], [], [], [], [], [], [], [], [], [], [], []], [[], [], [], [], [], [], [], [], [], [], [], [], [], [], [], [], [], [], [], [], [], [], [], [], [], [], [], [], [], [], [], [], [], [], [], [], [], [], [], [], [], [], [], [], [], [], [], [], [], []], [[], [], [], [], [], [], [], [], [], [], [], [], [], [], [], [], [], [], [], [], [], [], [], [], [], [], [], [], [], [], [], [], [], [], [], [], [], [], [], [], [], [], [], [], [], [], [], [], [], []], [[], [], [], [], [], [], [], [], [], [], [], [], [], [], [], [], [], [], [], [], [], [], [], [], [], [], [], [], [], [], [], [], [], [], [], [], [], [], [], [], [], [], [], [], [], [], [], [], [], []], [[], [], [], [], [], [], [], [], [], [], [], [], [], [], [], [], [], [], [], [], [], [], [], [], [], [], [], [], [], [], [], [], [], [], [], [], [], [], [], [], [], [], [], [], [], [], [], [], [], []]], "water": []}, "Trees": [[5, true, 0], [5, true, 0], [5, true, 0], [5, true, 0], [5, true, 0], [5, true, 0], [5, true, 0], [5, true, 0], [5, true, 0], [5, true, 0], [5, true, 0], [5, true, 0], [5, true, 0], [5, true, 0], [5, true, 0], [5, true, 0], [5, true, 0], [5, true, 0], [5, true, 0], [5, true, 0], [5, true, 0], [5, true, 0], [5, true, 0], [5, true, 0], [5, true, 0], [5, true, 0], [5, true, 0], [5, true, 0], [5, true, 0], [5, true, 0]], "Plants": [["corn", 2, false], ["corn", 2, false], ["tomato", 1.4, false], ["tomato", 1.4, false], ["tomato", 1.4, false]]}